setup.py
mybond/__init__.py
mybond/settings.py
mybond/urls.py
mybond/wsgi.py
mybond.egg-info/PKG-INFO
mybond.egg-info/SOURCES.txt
mybond.egg-info/dependency_links.txt
mybond.egg-info/top_level.txt