Metadata-Version: 1.0
Name: mybond
Version: 0.1
Summary: good job
Home-page: http://www.naver.com
Author: bond
Author-email: mhr.bond@gmail.com
License: UNKNOWN
Platform: UNKNOWN
